fileseq/__init__.py
fileseq/__version__.py
fileseq/constants.py
fileseq/exceptions.py
fileseq/filesequence.py
fileseq/frameset.py
fileseq/py.typed
fileseq/utils.py
fileseq-2.2.0.dist-info/licenses/LICENSE
fileseq-2.2.0.dist-info/METADATA
fileseq-2.2.0.dist-info/WHEEL
fileseq-2.2.0.dist-info/top_level.txt
fileseq-2.2.0.dist-info/RECORD
