Metadata-Version: 2.4
Name: Fileseq
Version: 2.2.0
Summary: A Python library for parsing frame ranges and file sequences commonly used in VFX and Animation applications.
Home-page: https://github.com/justinfx/fileseq
Author: Matt Chambers
Author-email: yougotrooted@gmail.com
Maintainer: Justin Israel
Maintainer-email: justinisrael@gmail.com
License: MIT
Keywords: vfx visual effects file sequence frames image
Classifier: Development Status :: 5 - Production/Stable
Classifier: License :: OSI Approved :: MIT License
Classifier: Programming Language :: Python :: 3.6
Classifier: Programming Language :: Python :: 3.7
Classifier: Programming Language :: Python :: 3.8
Classifier: Programming Language :: Python :: 3.9
Classifier: Programming Language :: Python :: 3.10
Classifier: Programming Language :: Python :: 3
License-File: LICENSE
Dynamic: author
Dynamic: author-email
Dynamic: classifier
Dynamic: description
Dynamic: description-content-type
Dynamic: home-page
Dynamic: keywords
Dynamic: license
Dynamic: license-file
Dynamic: maintainer
Dynamic: maintainer-email
Dynamic: summary
